evt3-0.1.0.dist-info/METADATA
evt3-0.1.0.dist-info/WHEEL
evt3/__init__.py
evt3/_evt3.cp311-win_amd64.pyd
evt3-0.1.0.dist-info/RECORD
