Metadata-Version: 2.4
Name: evt3
Version: 0.1.0
Classifier: Development Status :: 4 - Beta
Classifier: Intended Audience :: Science/Research
Classifier: License :: OSI Approved :: MIT License
Classifier: Programming Language :: Rust
Classifier: Programming Language :: Python :: Implementation :: CPython
Classifier: Programming Language :: Python :: 3
Classifier: Programming Language :: Python :: 3.8
Classifier: Programming Language :: Python :: 3.9
Classifier: Programming Language :: Python :: 3.10
Classifier: Programming Language :: Python :: 3.11
Classifier: Programming Language :: Python :: 3.12
Classifier: Topic :: Scientific/Engineering
Classifier: Topic :: Scientific/Engineering :: Image Processing
Classifier: Topic :: Multimedia :: Video
Requires-Dist: numpy>=1.20
Requires-Dist: pytest>=7.0 ; extra == 'dev'
Requires-Dist: maturin>=1.4 ; extra == 'dev'
Requires-Dist: pandas>=1.3 ; extra == 'dev'
Provides-Extra: dev
Summary: High-performance EVT 3.0 decoder for Prophesee event cameras
Keywords: event-camera,evt3,prophesee,decoder,neuromorphic,dvs
Author-email: Uthmann <mika.uthmann@uni-bielefeld.de>
License: MIT
Requires-Python: >=3.8
Project-URL: Homepage, https://github.com/muthmann/evt3
Project-URL: Repository, https://github.com/muthmann/evt3
Project-URL: Documentation, https://github.com/muthmann/evt3#readme
Project-URL: Bug Tracker, https://github.com/muthmann/evt3/issues
